{"ongoing_trials": {"tuner0": "003"}, "hyperparameters": {"space": [{"class_name": "Int", "config": {"name": "num_layers", "default": null, "conditions": [], "min_value": 1, "max_value": 4, "step": 1, "sampling": "linear"}}, {"class_name": "Int", "config": {"name": "units_0", "default": null, "conditions": [], "min_value": 16, "max_value": 128, "step": 16, "sampling": "linear"}}, {"class_name": "Choice", "config": {"name": "activation_0", "default": "relu", "conditions": [], "values": ["relu", "tanh"], "ordered": false}}, {"class_name": "Choice", "config": {"name": "recurrent_activation_0", "default": "sigmoid", "conditions": [], "values": ["sigmoid", "relu"], "ordered": false}}, {"class_name": "Float", "config": {"name": "dropout_0", "default": 0.0, "conditions": [], "min_value": 0.0, "max_value": 0.6, "step": 0.1, "sampling": "linear"}}, {"class_name": "Float", "config": {"name": "recurrent_dropout_0", "default": 0.0, "conditions": [], "min_value": 0.0, "max_value": 0.6, "step": 0.1, "sampling": "linear"}}, {"class_name": "Choice", "config": {"name": "activation_1", "default": "sigmoid", "conditions": [], "values": ["sigmoid", "relu"], "ordered": false}}, {"class_name": "Float", "config": {"name": "lr", "default": 0.0001, "conditions": [], "min_value": 0.0001, "max_value": 0.1, "step": null, "sampling": "log"}}, {"class_name": "Int", "config": {"name": "units_1", "default": null, "conditions": [], "min_value": 16, "max_value": 128, "step": 16, "sampling": "linear"}}, {"class_name": "Choice", "config": {"name": "recurrent_activation_1", "default": "sigmoid", "conditions": [], "values": ["sigmoid", "relu"], "ordered": false}}, {"class_name": "Float", "config": {"name": "dropout_1", "default": 0.0, "conditions": [], "min_value": 0.0, "max_value": 0.6, "step": 0.1, "sampling": "linear"}}, {"class_name": "Float", "config": {"name": "recurrent_dropout_1", "default": 0.0, "conditions": [], "min_value": 0.0, "max_value": 0.6, "step": 0.1, "sampling": "linear"}}, {"class_name": "Choice", "config": {"name": "activation_2", "default": "sigmoid", "conditions": [], "values": ["sigmoid", "relu"], "ordered": false}}], "values": {"num_layers": 1, "units_0": 16, "activation_0": "relu", "recurrent_activation_0": "sigmoid", "dropout_0": 0.0, "recurrent_dropout_0": 0.0, "activation_1": "sigmoid", "lr": 0.0001, "units_1": 16, "recurrent_activation_1": "sigmoid", "dropout_1": 0.0, "recurrent_dropout_1": 0.0, "activation_2": "sigmoid"}}, "start_order": ["000", "001", "002", "003"], "end_order": ["000", "001", "002"], "run_times": {"000": 1, "001": 1, "002": 1}, "retry_queue": [], "seed": 7058, "seed_state": 7100, "tried_so_far": ["ab6b031949a21c39c6653cd8021859ba", "779c7ed5faa3337f52c2d1fa2d7b5b78", "a77cbbbdd366133e3bf079b66273039d", "de8d700e2424ed54561336fb1da18dc5"], "id_to_hash": {"000": "de8d700e2424ed54561336fb1da18dc5", "001": "ab6b031949a21c39c6653cd8021859ba", "002": "779c7ed5faa3337f52c2d1fa2d7b5b78", "003": "a77cbbbdd366133e3bf079b66273039d"}, "display": {"search_start": "2024-08-02T16:03:26.815089", "trial_start": {"000": "2024-08-02T16:03:26.815089", "001": "2024-08-02T16:04:33.543852", "002": "2024-08-02T16:05:58.898936"}, "trial_number": {"000": 1, "001": 2, "002": 3}}}